{
    "obstacles": [
        { "x": 100, "y": 300, "type": "tiles", "frame": 0 },
        { "x": 200, "y": 300, "type": "tiles", "frame": 0 },
        { "x": 280, "y": 300, "type": "tiles", "frame": 0 },
        { "x": 200, "y": 370, "type": "tiles", "frame": 0 },
        { "x": 280, "y": 370, "type": "tiles", "frame": 0 },
        { "x": 400, "y": 100, "type": "tiles", "frame": 0 },
        { "x": 400, "y": 170, "type": "tiles", "frame": 0 },
        { "x": 400, "y": 240, "type": "tiles", "frame": 0 },
        { "x": 400, "y": 310, "type": "tiles", "frame": 0 },
        { "x": 520, "y": 300, "type": "tiles", "frame": 0 },
        { "x": 520, "y": 370, "type": "tiles", "frame": 0 },
        { "x": 640, "y": 100, "type": "tiles", "frame": 0 },
        { "x": 640, "y": 170, "type": "tiles", "frame": 0 },
        { "x": 640, "y": 240, "type": "tiles", "frame": 0 },
        { "x": 640, "y": 310, "type": "tiles", "frame": 0 },
        { "x": 800, "y": 300, "type": "tiles", "frame": 0 },
        { "x": 800, "y": 370, "type": "tiles", "frame": 0 },
        { "x": 1000, "y": 170, "type": "tiles", "frame": 0 },
        { "x": 1080, "y": 240, "type": "tiles", "frame": 0 },
        { "x": 1160, "y": 310, "type": "tiles", "frame": 0 },
        { "x": 1240, "y": 300, "type": "tiles", "frame": 0 },
        { "x": 1320, "y": 370, "type": "tiles", "frame": 0 },
        { "x": 1400, "y": 100, "type": "tiles", "frame": 0 },
        { "x": 1480, "y": 170, "type": "tiles", "frame": 0 },
        { "x": 1560, "y": 240, "type": "tiles", "frame": 0 },
        { "x": 1640, "y": 310, "type": "tiles", "frame": 0 },
        { "x": 1720, "y": 300, "type": "tiles", "frame": 0 },
        { "x": 1960, "y": 170, "type": "tiles", "frame": 0 },
        { "x": 2040, "y": 240, "type": "tiles", "frame": 0 },
        { "x": 2120, "y": 310, "type": "tiles", "frame": 0 },
        { "x": 2200, "y": 300, "type": "tiles", "frame": 0 },
        { "x": 2280, "y": 370, "type": "tiles", "frame": 0 },
        { "x": 2440, "y": 170, "type": "tiles", "frame": 0 },
        { "x": 2520, "y": 240, "type": "tiles", "frame": 0 },
        { "x": 2600, "y": 310, "type": "tiles", "frame": 0 },
        { "x": 2680, "y": 300, "type": "tiles", "frame": 0 },
        { "x": 2920, "y": 170, "type": "tiles", "frame": 0 },
        { "x": 3000, "y": 240, "type": "tiles", "frame": 0 },
        { "x": 3080, "y": 310, "type": "tiles", "frame": 0 },
        { "x": 3160, "y": 300, "type": "tiles", "frame": 0 },
        { "x": 3400, "y": 170, "type": "tiles", "frame": 0 },
        { "x": 3480, "y": 240, "type": "tiles", "frame": 0 },
        { "x": 3560, "y": 310, "type": "tiles", "frame": 0 },
        { "x": 3640, "y": 300, "type": "tiles", "frame": 0 },
        { "x": 3880, "y": 170, "type": "tiles", "frame": 0 },
        { "x": 3880, "y": 100, "type": "tiles", "frame": 0 },
        { "x": 3960, "y": 240, "type": "tiles", "frame": 0 },
        { "x": 4120, "y": 300, "type": "tiles", "frame": 0 },
        { "x": 4200, "y": 370, "type": "tiles", "frame": 0 },
        { "x": 4360, "y": 170, "type": "tiles", "frame": 0 },
        { "x": 4360, "y": 100, "type": "tiles", "frame": 0 },
        { "x": 4440, "y": 240, "type": "tiles", "frame": 0 },
        { "x": 4520, "y": 310, "type": "tiles", "frame": 0 },
        { "x": 4600, "y": 300, "type": "tiles", "frame": 0 },
        { "x": 4840, "y": 170, "type": "tiles", "frame": 0 },
        { "x": 4920, "y": 240, "type": "tiles", "frame": 0 }
    ]
}
